{
  "type": "Feature",
  "properties": {
    "gn:gn_country":"GG",
    "gn:gn_fcode":"PPL",
    "gn:gn_pop":0,
    "iso:country":"GG",
    "name:eng_x_preferred":[
        "Calais"
    ],
    "qs_pg:aaroncc":"GG",
    "qs_pg:gn_country":"GG",
    "qs_pg:gn_fcode":"PPL",
    "qs_pg:gn_pop":0,
    "qs_pg:name":"Calais",
    "qs_pg:name_adm0":"United Kingdom",
    "qs_pg:name_adm1":"Channel Islands",
    "qs_pg:photos":212,
    "qs_pg:photos_1k":43,
    "qs_pg:photos_9k":1,
    "qs_pg:photos_9r":4,
    "qs_pg:photos_all":212,
    "qs_pg:photos_sr":4,
    "qs_pg:pop_sr":0,
    "qs_pg:qs_pg_placetype":"locality",
    "qs_pg:qs_pg_placetype_gp":"Town",
    "qs_pg:woe_adm0":23424975,
    "woe:adm0_id":23424975,
    "woe:name_adm0":"United Kingdom",
    "woe:name_adm1":"Channel Islands",
    "woe:placetype":"Town",
    "wof:name":"Calais",
    "wof:placetype":"locality"
},
  "geometry": {"coordinates":[-2.53972,49.43361],"type":"Point"}
}