{
  "type": "Feature",
  "properties": {
    "gn:admin1_code":"00",
    "gn:asciiname":"Les Hurlaux",
    "gn:country_code":"GG",
    "gn:dem":88,
    "gn:feature_class":"P",
    "gn:feature_code":"PPL",
    "gn:name":"Les Hurlaux",
    "gn:population":0,
    "gn:timezone":"Europe/Guernsey",
    "iso:country":"GG",
    "name:eng_x_preferred":[
        "Les Hurlaux"
    ],
    "wof:name":"Les Hurlaux",
    "wof:placetype":"locality"
},
  "geometry": {"coordinates":[-2.56194,49.44389],"type":"Point"}
}