{
  "type": "Feature",
  "properties": {
    "gn:admin1_code":"6417213",
    "gn:asciiname":"Les Adams",
    "gn:country_code":"GG",
    "gn:dem":10,
    "gn:feature_class":"P",
    "gn:feature_code":"PPL",
    "gn:name":"Les Adams",
    "gn:population":0,
    "gn:timezone":"Europe/Guernsey",
    "iso:country":"GG",
    "name:eng_x_preferred":[
        "Les Adams"
    ],
    "wof:name":"Les Adams",
    "wof:placetype":"locality"
},
  "geometry": {"coordinates":[-2.64611,49.45361],"type":"Point"}
}