{
  "type": "Feature",
  "properties": {
    "gn:admin1_code":"00",
    "gn:asciiname":"La Ramee",
    "gn:country_code":"GG",
    "gn:dem":12,
    "gn:feature_class":"P",
    "gn:feature_code":"PPL",
    "gn:name":"La Ram\u00e9e",
    "gn:population":0,
    "gn:timezone":"Europe/Guernsey",
    "iso:country":"GG",
    "name:eng_x_preferred":[
        "La Ram\u00e9e"
    ],
    "name:und_x_variant":[
        "Ramee"
    ],
    "wof:name":"La Ramee",
    "wof:placetype":"locality"
},
  "geometry": {"coordinates":[-2.55611,49.47139],"type":"Point"}
}