{
  "type": "Feature",
  "properties": {
    "gn:admin1_code":"00",
    "gn:asciiname":"Les Mielles",
    "gn:country_code":"GG",
    "gn:dem":8,
    "gn:feature_class":"P",
    "gn:feature_code":"PPL",
    "gn:name":"Les Mielles",
    "gn:population":0,
    "gn:timezone":"Europe/Guernsey",
    "iso:country":"GG",
    "name:eng_x_preferred":[
        "Les Mielles"
    ],
    "wof:name":"Les Mielles",
    "wof:placetype":"locality"
},
  "geometry": {"coordinates":[-2.52028,49.49889],"type":"Point"}
}