{
  "type": "Feature",
  "properties": {
    "gn:admin1_code":"00",
    "gn:asciiname":"La Garenne",
    "gn:country_code":"GG",
    "gn:dem":7,
    "gn:feature_class":"P",
    "gn:feature_code":"PPL",
    "gn:name":"La Garenne",
    "gn:population":0,
    "gn:timezone":"Europe/Guernsey",
    "iso:country":"GG",
    "name:eng_x_preferred":[
        "La Garenne"
    ],
    "name:fra_x_preferred":[
        "La Garenne"
    ],
    "name:swe_x_preferred":[
        "La Garenne"
    ],
    "wof:name":"La Garenne",
    "wof:placetype":"locality"
},
  "geometry": {"coordinates":[-2.54,49.49444],"type":"Point"}
}