{
  "type": "Feature",
  "properties": {
    "gn:admin1_code":"00",
    "gn:asciiname":"La Forge",
    "gn:country_code":"GG",
    "gn:dem":87,
    "gn:feature_class":"P",
    "gn:feature_code":"PPL",
    "gn:name":"La Forge",
    "gn:population":0,
    "gn:timezone":"Europe/Guernsey",
    "iso:country":"GG",
    "name:deu_x_preferred":[
        "La Forge"
    ],
    "name:eng_x_preferred":[
        "La Forge"
    ],
    "name:fra_x_preferred":[
        "La Forge"
    ],
    "wof:name":"La Forge",
    "wof:placetype":"locality"
},
  "geometry": {"coordinates":[-2.35083,49.42917],"type":"Point"}
}