{
  "type": "Feature",
  "properties": {
    "gn:admin1_code":"00",
    "gn:asciiname":"Les Maingys",
    "gn:country_code":"GG",
    "gn:dem":9,
    "gn:feature_class":"P",
    "gn:feature_code":"PPL",
    "gn:name":"Les Maingys",
    "gn:population":0,
    "gn:timezone":"Europe/Guernsey",
    "iso:country":"GG",
    "name:eng_x_preferred":[
        "Les Maingys"
    ],
    "wof:name":"Les Maingys",
    "wof:placetype":"locality"
},
  "geometry": {"coordinates":[-2.57,49.48333],"type":"Point"}
}