{
  "type": "Feature",
  "properties": {
    "gn:admin1_code":"00",
    "gn:asciiname":"Le Chene",
    "gn:country_code":"GG",
    "gn:dem":95,
    "gn:feature_class":"P",
    "gn:feature_code":"PPL",
    "gn:name":"Le Ch\u00e9ne",
    "gn:population":0,
    "gn:timezone":"Europe/Guernsey",
    "iso:country":"GG",
    "name:eng_x_preferred":[
        "Le Ch\u00e9ne"
    ],
    "wof:name":"Le Chene",
    "wof:placetype":"locality"
},
  "geometry": {"coordinates":[-2.58583,49.43222],"type":"Point"}
}