{
  "type": "Feature",
  "properties": {
    "gn:admin1_code":"00",
    "gn:asciiname":"Cocagne",
    "gn:country_code":"GG",
    "gn:dem":7,
    "gn:feature_class":"P",
    "gn:feature_code":"PPL",
    "gn:name":"Cocagne",
    "gn:population":0,
    "gn:timezone":"Europe/Guernsey",
    "iso:country":"GG",
    "name:eng_x_preferred":[
        "Cocagne"
    ],
    "wof:name":"Cocagne",
    "wof:placetype":"locality"
},
  "geometry": {"coordinates":[-2.50861,49.49222],"type":"Point"}
}