{
  "type": "Feature",
  "properties": {
    "gn:admin1_code":"00",
    "gn:asciiname":"Mouilpied",
    "gn:country_code":"GG",
    "gn:dem":97,
    "gn:feature_class":"P",
    "gn:feature_code":"PPL",
    "gn:name":"Mouilpied",
    "gn:population":0,
    "gn:timezone":"Europe/Guernsey",
    "iso:country":"GG",
    "name:eng_x_preferred":[
        "Mouilpied"
    ],
    "wof:name":"Mouilpied",
    "wof:placetype":"locality"
},
  "geometry": {"coordinates":[-2.56806,49.43667],"type":"Point"}
}