{
  "type": "Feature",
  "properties": {
    "gn:admin1_code":"00",
    "gn:asciiname":"La Houguette",
    "gn:country_code":"GG",
    "gn:dem":38,
    "gn:feature_class":"P",
    "gn:feature_code":"PPL",
    "gn:name":"La Houguette",
    "gn:population":0,
    "gn:timezone":"Europe/Guernsey",
    "iso:country":"GG",
    "name:eng_x_preferred":[
        "La Houguette"
    ],
    "wof:name":"La Houguette",
    "wof:placetype":"locality"
},
  "geometry": {"coordinates":[-2.63917,49.45],"type":"Point"}
}