{
  "type": "Feature",
  "properties": {
    "iso:country":"GG",
    "qs_pg:aaroncc":"GG",
    "qs_pg:name":"St. Anne",
    "qs_pg:name_adm0":"United Kingdom",
    "qs_pg:name_adm1":"Channel Islands",
    "qs_pg:photos":243,
    "qs_pg:photos_1k":49,
    "qs_pg:photos_9k":1,
    "qs_pg:photos_9r":4,
    "qs_pg:photos_all":243,
    "qs_pg:photos_sr":4,
    "qs_pg:pop_sr":0,
    "qs_pg:qs_pg_placetype":"locality",
    "qs_pg:qs_pg_placetype_gp":"Town",
    "qs_pg:woe_adm0":23424975,
    "woe:adm0_id":23424975,
    "woe:name_adm0":"United Kingdom",
    "woe:name_adm1":"Channel Islands",
    "woe:placetype":"Town",
    "wof:name":"St. Anne",
    "wof:placetype":"locality"
},
  "geometry": {"coordinates":[-2.228851,49.706054],"type":"Point"}
}