{
  "type": "Feature",
  "properties": {
    "iso:country":"GG",
    "name:ceb_x_preferred":[
        "Vale"
    ],
    "name:deu_x_preferred":[
        "Vale"
    ],
    "name:epo_x_preferred":[
        "Vale"
    ],
    "name:fin_x_preferred":[
        "Vale"
    ],
    "name:fra_x_preferred":[
        "Vale"
    ],
    "name:glg_x_preferred":[
        "Vale"
    ],
    "name:hun_x_preferred":[
        "Vale"
    ],
    "name:ita_x_preferred":[
        "Vale"
    ],
    "name:nld_x_preferred":[
        "Vale"
    ],
    "name:nor_x_preferred":[
        "Vale"
    ],
    "name:pol_x_preferred":[
        "Vale"
    ],
    "name:por_x_preferred":[
        "Vale"
    ],
    "name:ron_x_preferred":[
        "Vale"
    ],
    "name:rus_x_preferred":[
        "Vale"
    ],
    "name:spa_x_preferred":[
        "Vale"
    ],
    "name:srp_x_preferred":[
        "\u0412\u0435\u0458\u043b"
    ],
    "name:swe_x_preferred":[
        "Vale"
    ],
    "qs_pg:aaroncc":"GG",
    "qs_pg:name":"Vale",
    "qs_pg:name_adm0":"United Kingdom",
    "qs_pg:name_adm1":"Channel Islands",
    "qs_pg:photos":8,
    "qs_pg:photos_1k":2,
    "qs_pg:photos_9k":17,
    "qs_pg:photos_9r":12,
    "qs_pg:photos_all":3860,
    "qs_pg:photos_sr":1,
    "qs_pg:pop_sr":0,
    "qs_pg:qs_pg_placetype":"localadmin",
    "qs_pg:qs_pg_placetype_gp":"LocalAdmin",
    "qs_pg:woe_adm0":23424975,
    "woe:adm0_id":23424975,
    "woe:name_adm0":"United Kingdom",
    "woe:name_adm1":"Channel Islands",
    "woe:placetype":"LocalAdmin",
    "wof:name":"Vale",
    "wof:placetype":"localadmin"
},
  "geometry": {"coordinates":[-2.509839,49.49666],"type":"Point"}
}