{
  "type": "Feature",
  "properties": {
    "iso:country":"GG",
    "qs_pg:aaroncc":"GG",
    "qs_pg:name":"St Peter Port",
    "qs_pg:name_adm0":"United Kingdom",
    "qs_pg:name_adm1":"Channel Islands",
    "qs_pg:photos":1433,
    "qs_pg:photos_1k":290,
    "qs_pg:photos_9k":20,
    "qs_pg:photos_9r":13,
    "qs_pg:photos_all":4507,
    "qs_pg:photos_sr":12,
    "qs_pg:pop_sr":0,
    "qs_pg:qs_pg_placetype":"localadmin",
    "qs_pg:qs_pg_placetype_gp":"LocalAdmin",
    "qs_pg:woe_adm0":23424975,
    "woe:adm0_id":23424975,
    "woe:name_adm0":"United Kingdom",
    "woe:name_adm1":"Channel Islands",
    "woe:placetype":"LocalAdmin",
    "wof:name":"St Peter Port",
    "wof:placetype":"localadmin"
},
  "geometry": {"coordinates":[-2.534837,49.456409],"type":"Point"}
}