{
  "type": "Feature",
  "properties": {
    "gn:admin1_code":"00",
    "gn:asciiname":"Friquet",
    "gn:country_code":"GG",
    "gn:dem":7,
    "gn:feature_class":"P",
    "gn:feature_code":"PPL",
    "gn:name":"Friquet",
    "gn:population":0,
    "gn:timezone":"Europe/Guernsey",
    "iso:country":"GG",
    "name:eng_x_preferred":[
        "Friquet"
    ],
    "wof:name":"Friquet",
    "wof:placetype":"locality"
},
  "geometry": {"coordinates":[-2.53139,49.49083],"type":"Point"}
}