{
  "type": "Feature",
  "properties": {
    "gn:admin1_code":"00",
    "gn:asciiname":"Four Cabot",
    "gn:country_code":"GG",
    "gn:dem":75,
    "gn:feature_class":"P",
    "gn:feature_code":"PPL",
    "gn:name":"Four Cabot",
    "gn:population":0,
    "gn:timezone":"Europe/Guernsey",
    "iso:country":"GG",
    "name:eng_x_preferred":[
        "Four Cabot"
    ],
    "wof:name":"Four Cabot",
    "wof:placetype":"locality"
},
  "geometry": {"coordinates":[-2.57389,49.44583],"type":"Point"}
}