{
  "type": "Feature",
  "properties": {
    "gn:admin1_code":"00",
    "gn:asciiname":"Le Gron",
    "gn:country_code":"GG",
    "gn:dem":86,
    "gn:feature_class":"P",
    "gn:feature_code":"PPL",
    "gn:name":"Le Gron",
    "gn:population":0,
    "gn:timezone":"Europe/Guernsey",
    "iso:country":"GG",
    "name:eng_x_preferred":[
        "Le Gron"
    ],
    "wof:name":"Le Gron",
    "wof:placetype":"locality"
},
  "geometry": {"coordinates":[-2.60861,49.43889],"type":"Point"}
}