{
  "type": "Feature",
  "properties": {
    "gn:gn_country":"GG",
    "gn:gn_fcode":"PPL",
    "gn:gn_pop":0,
    "iso:country":"GG",
    "name:eng_x_preferred":[
        "La Villiaze"
    ],
    "qs_pg:aaroncc":"GG",
    "qs_pg:gn_country":"GG",
    "qs_pg:gn_fcode":"PPL",
    "qs_pg:gn_pop":0,
    "qs_pg:name":"La Villiaze",
    "qs_pg:name_adm0":"United Kingdom",
    "qs_pg:name_adm1":"Channel Islands",
    "qs_pg:photos":131,
    "qs_pg:photos_1k":27,
    "qs_pg:photos_9k":1,
    "qs_pg:photos_9r":3,
    "qs_pg:photos_all":131,
    "qs_pg:photos_sr":3,
    "qs_pg:pop_sr":0,
    "qs_pg:qs_pg_placetype":"locality",
    "qs_pg:qs_pg_placetype_gp":"Town",
    "qs_pg:woe_adm0":23424975,
    "woe:adm0_id":23424975,
    "woe:name_adm0":"United Kingdom",
    "woe:name_adm1":"Channel Islands",
    "woe:placetype":"Town",
    "wof:name":"La Villiaze",
    "wof:placetype":"locality"
},
  "geometry": {"coordinates":[-2.59167,49.4375],"type":"Point"}
}